Workbook

Sheet  C O N T A S 
C1: Confronto Inicial
E2: Total do relatório | F2: Diferença
C3: Valor Transportado | D3: =SUM(I64:I270)/2 -> 191990.22 | E3: =+[1]DesSin02.rpt!$F$135 -> 0 | F3: =+E3-D3 -> -191990.22 | G3: verificar se a diferença para o total do relatório é igual ao evento ESTORNO
C4: Desconsiderações | D4: =+SUM(I101:I103,I105,I106)+I131+SUM(I140:I142)+I150+I153+I154+I159+I160+I164+I166+I168+I169+I216+I220+I226+I230+I243+I250+I257 -> 2459.29
C5: Subtotal Inicial | D5: =D3-D4 -> 189530.93
C7: Subtotal Atual | D7: =' P R E V I S Ã O '!D48 -> 189530.93
D10: 0
A11: 1 | B11: - | C11: Plano Basico
A12: 01 | C12: Receitas Operacionais (mês) | D12: =SUM(D13:D62) -> 19787.86
B14: 01.01 | C14: Receitas Gerais | D14: 0
B15: 01.02 | C15: Tx. Condomínio | D15: 15446.72
B16: 01.03 | C16: Fundo Reserva | D16: 1544.56
B17: 01.04 | C17: Fundo de Obras
B18: 01.05 | C18: Taxa de Administração
B19: 01.06 | C19: Taxa Extra
B20: 01.07 | C20: Gás
B21: 01.08 | C21: Compl.Tx.Condomínio
B22: 01.09 | C22: Luz
B23: 01.10 | C23: Telefone
B24: 01.11 | C24: Tv a Cabo
B25: 01.12 | C25: Crédito
B26: 01.13 | C26: Taxa Extra.
B27: 01.14 | C27: Tx. Extra Reforma do Prédio
B28: 01.15 | C28: Parc.Acordo/Processo N. 25427
... B48: 01.35 | C48: Fundo de Verão
B49: 01.36 | C49: Água | D49: 2796.58
B50: 01.37 | C50: Energia
B51: 01.38 | C51: Locação
B52: 01.39 | C52: Salão de Festas / Churrasqueira
B53: 01.40 | C53: Transferência para a aplicação/poupança
B54: 01.41 | C54: Resgate da conta de aplicação/poupança
B55: 01.42 | C55: Rateio Gás/Internet/TV
B56: 01.43 | C56: Sistema contra incêndio
B57: 01.44 | C57: Taxa extra - D.P.
B58: 01.45 | C58: Fundo de Melhoria
B59: 01.46 | C59: Pró-Labore
B60: 01.47 | C60: Aluguel de Espaço p/ Antena de Telefonia
B61: 01.48 | C61: Energia Elétrica da Antena de Telefonia
B62: 01.99 | C62: Outros
A64: 02 | C64: Despesas com Pessoal | D64: =SUM(D66:D93) -> 50680.23 | I64: =SUM(I66:I94) -> 50680.23
B66: 02.01 | C66: Salário Empregado(s) | D66: =IF(ISERROR(VLOOKUP(C66,[1]DesSin02.rpt!$A$1:$H$200,6,FALSE))=TRUE,0,VLOOKUP(C66,[1]DesSin02.rpt!$A$1:$H$200,6,FALSE)) -> 28300.55 | I66: =D66-SUM(E66:H66) -> 28300.55
B67: 02.02 | C67: INSS/IRRF/Pis/Cofins/CSLL | D67: =IF(ISERROR(VLOOKUP(C67,[1]DesSin02.rpt!$A$1:$H$200,6,FALSE))=TRUE,0,VLOOKUP(C67,[1]DesSin02.rpt!$A$1:$H$200,6,FALSE)) -> 11463.07 | I67: =D67-SUM(E67:H67) -> 11463.07
B68: 02.03 | C68: Pis | D68: =IF(ISERROR(VLOOKUP(C68,[1]DesSin02.rpt!$A$1:$H$200,6,FALSE))=TRUE,0,VLOOKUP(C68,[1]DesSin02.rpt!$A$1:$H$200,6,FALSE)) -> 0 | I68: =D68-SUM(E68:H68) -> 0
B69: 02.04 | C69: INSS S/13. Salário | D69: =IF(ISERROR(VLOOKUP(C69,[1]DesSin02.rpt!$A$1:$H$200,6,FALSE))=TRUE,0,VLOOKUP(C69,[1]DesSin02.rpt!$A$1:$H$200,6,FALSE)) -> 887.14 | I69: =D69-SUM(E69:H69) -> 887.14
B70: 02.05 | C70: Vale Transporte | D70: =IF(ISERROR(VLOOKUP(C70,[1]DesSin02.rpt!$A$1:$H$200,6,FALSE))=TRUE,0,VLOOKUP(C70,[1]DesSin02.rpt!$A$1:$H$200,6,FALSE)) -> 0 | I70: =D70-SUM(E70:H70) -> 0
B71: 02.06 | C71: Consult., Medicina e Seg. do Trabalho | D71: =IF(ISERROR(VLOOKUP(C71,[1]DesSin02.rpt!$A$1:$H$200,6,FALSE))=TRUE,0,VLOOKUP(C71,[1]DesSin02.rpt!$A$1:$H$200,6,FALSE)) -> 651 | I71: =D71-SUM(E71:H71) -> 651
B72: 02.07 | C72: Contrato Médico de Saúde | D72: =IF(ISERROR(VLOOKUP(C72,[1]DesSin02.rpt!$A$1:$H$200,6,FALSE))=TRUE,0,VLOOKUP(C72,[1]DesSin02.rpt!$A$1:$H$200,6,FALSE)) -> 0 | I72: =D72-SUM(E72:H72) -> 0
B73: 02.08 | C73: 13º Salário Empregado(s) | D73: =IF(ISERROR(VLOOKUP(C73,[1]DesSin02.rpt!$A$1:$H$200,6,FALSE))=TRUE,0,VLOOKUP(C73,[1]DesSin02.rpt!$A$1:$H$200,6,FALSE)) -> 2356 | I73: =D73-SUM(E73:H73) -> 2356
B74: 02.09 | C74: FGTS | D74: =IF(ISERROR(VLOOKUP(C74,[1]DesSin02.rpt!$A$1:$H$200,6,FALSE))=TRUE,0,VLOOKUP(C74,[1]DesSin02.rpt!$A$1:$H$200,6,FALSE)) -> 2713.63 | I74: =D74-SUM(E74:H74) -> 2713.63
B75: 02.10 | C75: Férias Empregado(s) | D75: =IF(ISERROR(VLOOKUP(C75,[1]DesSin02.rpt!$A$1:$H$200,6,FALSE))=TRUE,0,VLOOKUP(C75,[1]DesSin02.rpt!$A$1:$H$200,6,FALSE)) -> 3231.94 | I75: =D75-SUM(E75:H75) -> 3231.94
B76: 02.11 | C76: Cesta Básica | D76: =IF(ISERROR(VLOOKUP(C76,[1]DesSin02.rpt!$A$1:$H$200,6,FALSE))=TRUE,0,VLOOKUP(C76,[1]DesSin02.rpt!$A$1:$H$200,6,FALSE)) -> 0 | I76: =D76-SUM(E76:H76) -> 0
B77: 02.12 | C77: Rescisão Trabalhista | D77: =IF(ISERROR(VLOOKUP(C77,[1]DesSin02.rpt!$A$1:$H$200,6,FALSE))=TRUE,0,VLOOKUP(C77,[1]DesSin02.rpt!$A$1:$H$200,6,FALSE)) -> 0 | I77: =D77-SUM(E77:H77) -> 0
... B93: 02.99 | C93: Outros | D93: =IF(ISERROR(VLOOKUP(C93,[1]DesSin02.rpt!$A$1:$H$200,6,FALSE))=TRUE,0,VLOOKUP(C93,[1]DesSin02.rpt!$A$1:$H$200,6,FALSE)) -> 633 | I93: =D93-SUM(E93:H93) -> 633
A96: 03 | C96: Tarifas Públicas | D96: =SUM(D98:D106) -> 69003.39 | I96: =SUM(I98:I107) -> 69003.39
B98: 03.01 | C98: Luz do Condomínio | D98: =IF(ISERROR(VLOOKUP(C98,[1]DesSin02.rpt!$A$1:$H$200,6,FALSE))=TRUE,0,VLOOKUP(C98,[1]DesSin02.rpt!$A$1:$H$200,6,FALSE)) -> 9700.19 | I98: =D98-SUM(E98:H98) -> 9700.19
B99: 03.02 | C99: Água do Condomínio | D99: =IF(ISERROR(VLOOKUP(C99,[1]DesSin02.rpt!$A$1:$H$200,6,FALSE))=TRUE,0,VLOOKUP(C99,[1]DesSin02.rpt!$A$1:$H$200,6,FALSE)) -> 59303.2 | I99: =D99-SUM(E99:H99) -> 59303.2
B100: 03.03 | C100: Telefone do Condomínio | D100: =IF(ISERROR(VLOOKUP(C100,[1]DesSin02.rpt!$A$1:$H$200,6,FALSE))=TRUE,0,VLOOKUP(C100,[1]DesSin02.rpt!$A$1:$H$200,6,FALSE)) -> 0 | I100: =D100-SUM(E100:H100) -> 0
B101: 03.04 | C101: Luz Apartamento(s) | D101: =IF(ISERROR(VLOOKUP(C101,[1]DesSin02.rpt!$A$1:$H$200,6,FALSE))=TRUE,0,VLOOKUP(C101,[1]DesSin02.rpt!$A$1:$H$200,6,FALSE)) -> 0 | I101: =D101-SUM(E101:H101) -> 0
B102: 03.05 | C102: Telefone Apartamento(s) | D102: =IF(ISERROR(VLOOKUP(C102,[1]DesSin02.rpt!$A$1:$H$200,6,FALSE))=TRUE,0,VLOOKUP(C102,[1]DesSin02.rpt!$A$1:$H$200,6,FALSE)) -> 0 | I102: =D102-SUM(E102:H102) -> 0
B103: 03.06 | C103: Luz do Zelador | D103: =IF(ISERROR(VLOOKUP(C103,[1]DesSin02.rpt!$A$1:$H$200,6,FALSE))=TRUE,0,VLOOKUP(C103,[1]DesSin02.rpt!$A$1:$H$200,6,FALSE)) -> 0 | I103: =D103-SUM(E103:H103) -> 0
B104: 03.07 | C104: Gás do Condomínio | D104: =IF(ISERROR(VLOOKUP(C104,[1]DesSin02.rpt!$A$1:$H$200,6,FALSE))=TRUE,0,VLOOKUP(C104,[1]DesSin02.rpt!$A$1:$H$200,6,FALSE)) -> 0 | I104: =D104-SUM(E104:H104) -> 0
B105: 03.08 | C105: Conta de Luz | D105: =IF(ISERROR(VLOOKUP(C105,[1]DesSin02.rpt!$A$1:$H$200,6,FALSE))=TRUE,0,VLOOKUP(C105,[1]DesSin02.rpt!$A$1:$H$200,6,FALSE)) -> 0 | I105: =D105-SUM(E105:H105) -> 0
B106: 03.09 | C106: Conta de Água | D106: =IF(ISERROR(VLOOKUP(C106,[1]DesSin02.rpt!$A$1:$H$200,6,FALSE))=TRUE,0,VLOOKUP(C106,[1]DesSin02.rpt!$A$1:$H$200,6,FALSE)) -> 0 | I106: =D106-SUM(E106:H106) -> 0
A108: 04 | C108: Conservação | D108: =SUM(D110:D134) -> 14148.53 | I108: =SUM(I110:I137) -> 19456.54
B110: 04.01 | C110: Manutenção Elétrica | D110: =IF(ISERROR(VLOOKUP(C110,[1]DesSin02.rpt!$A$1:$H$200,6,FALSE))=TRUE,0,VLOOKUP(C110,[1]DesSin02.rpt!$A$1:$H$200,6,FALSE)) -> 1025.28 | E110: 630 | I110: =D110-SUM(E110:H110) -> 395.28
B111: 04.02 | C111: Manutenção Hidráulica | D111: =IF(ISERROR(VLOOKUP(C111,[1]DesSin02.rpt!$A$1:$H$200,6,FALSE))=TRUE,0,VLOOKUP(C111,[1]DesSin02.rpt!$A$1:$H$200,6,FALSE)) -> 0 | I111: =D111-SUM(E111:H111) -> 0
B112: 04.03 | C112: Pequenas Reformas e Reparos | D112: =IF(ISERROR(VLOOKUP(C112,[1]DesSin02.rpt!$A$1:$H$200,6,FALSE))=TRUE,0,VLOOKUP(C112,[1]DesSin02.rpt!$A$1:$H$200,6,FALSE)) -> 0 | I112: =D112-SUM(E112:H112) -> 0
B113: 04.04 | C113: Manutenção de Máquinas | D113: =IF(ISERROR(VLOOKUP(C113,[1]DesSin02.rpt!$A$1:$H$200,6,FALSE))=TRUE,0,VLOOKUP(C113,[1]DesSin02.rpt!$A$1:$H$200,6,FALSE)) -> 0 | I113: =D113-SUM(E113:H113) -> 0
B114: 04.05 | C114: Manutenção de Jardim | D114: =IF(ISERROR(VLOOKUP(C114,[1]DesSin02.rpt!$A$1:$H$200,6,FALSE))=TRUE,0,VLOOKUP(C114,[1]DesSin02.rpt!$A$1:$H$200,6,FALSE)) -> 0 | I114: =D114-SUM(E114:H114) -> 0
B115: 04.06 | C115: Outros Materiais | D115: =IF(ISERROR(VLOOKUP(C115,[1]DesSin02.rpt!$A$1:$H$200,6,FALSE))=TRUE,0,VLOOKUP(C115,[1]DesSin02.rpt!$A$1:$H$200,6,FALSE)) -> 1575.32 | E115: 1000 | I115: =D115-SUM(E115:H115) -> 575.32
B116: 04.07 | C116: Serviço de Faxina | D116: =IF(ISERROR(VLOOKUP(C116,[1]DesSin02.rpt!$A$1:$H$200,6,FALSE))=TRUE,0,VLOOKUP(C116,[1]DesSin02.rpt!$A$1:$H$200,6,FALSE)) -> 0 | I116: =D116-SUM(E116:H116) -> 0
B117: 04.08 | C117: Dedetização/Descupinização | D117: =IF(ISERROR(VLOOKUP(C117,[1]DesSin02.rpt!$A$1:$H$200,6,FALSE))=TRUE,0,VLOOKUP(C117,[1]DesSin02.rpt!$A$1:$H$200,6,FALSE)) -> 400 | I117: =D117-SUM(E117:H117) -> 400
B118: 04.09 | C118: Uniformes(conta inativa) | D118: =IF(ISERROR(VLOOKUP(C118,[1]DesSin02.rpt!$A$1:$H$200,6,FALSE))=TRUE,0,VLOOKUP(C118,[1]DesSin02.rpt!$A$1:$H$200,6,FALSE)) -> 0 | I118: =D118-SUM(E118:H118) -> 0
B119: 04.10 | C119: Material de Limpeza | D119: =IF(ISERROR(VLOOKUP(C119,[1]DesSin02.rpt!$A$1:$H$200,6,FALSE))=TRUE,0,VLOOKUP(C119,[1]DesSin02.rpt!$A$1:$H$200,6,FALSE)) -> 2649.6 | I119: =D119-SUM(E119:H119) -> 2649.6
B120: 04.11 | C120: Manutenção Interfone | D120: =IF(ISERROR(VLOOKUP(C120,[1]DesSin02.rpt!$A$1:$H$200,6,FALSE))=TRUE,0,VLOOKUP(C120,[1]DesSin02.rpt!$A$1:$H$200,6,FALSE)) -> 0 | I120: =D120-SUM(E120:H120) -> 0
B121: 04.12 | C121: Manutenção Portão | D121: =IF(ISERROR(VLOOKUP(C121,[1]DesSin02.rpt!$A$1:$H$200,6,FALSE))=TRUE,0,VLOOKUP(C121,[1]DesSin02.rpt!$A$1:$H$200,6,FALSE)) -> 1140 | E121: 990 | I121: =D121-SUM(E121:H121) -> 150
B122: 04.13 | C122: Manutenção Piscina/E.T.A. | D122: =IF(ISERROR(VLOOKUP(C122,[1]DesSin02.rpt!$A$1:$H$200,6,FALSE))=TRUE,0,VLOOKUP(C122,[1]DesSin02.rpt!$A$1:$H$200,6,FALSE)) -> 1732 | I122: =D122-SUM(E122:H122) -> 1732
B123: 04.14 | C123: Manutenção Antena | D123: =IF(ISERROR(VLOOKUP(C123,[1]DesSin02.rpt!$A$1:$H$200,6,FALSE))=TRUE,0,VLOOKUP(C123,[1]DesSin02.rpt!$A$1:$H$200,6,FALSE)) -> 0 | I123: =D123-SUM(E123:H123) -> 0
B124: 04.15 | C124: Manutenção Pintura | D124: =IF(ISERROR(VLOOKUP(C124,[1]DesSin02.rpt!$A$1:$H$200,6,FALSE))=TRUE,0,VLOOKUP(C124,[1]DesSin02.rpt!$A$1:$H$200,6,FALSE)) -> 0 | I124: =D124-SUM(E124:H124) -> 0
B125: 04.16 | C125: Manutenção de Porta | D125: =IF(ISERROR(VLOOKUP(C125,[1]DesSin02.rpt!$A$1:$H$200,6,FALSE))=TRUE,0,VLOOKUP(C125,[1]DesSin02.rpt!$A$1:$H$200,6,FALSE)) -> 0 | I125: =D125-SUM(E125:H125) -> 0
B126: 04.17 | C126: Manut. Extintores | D126: 410.5 | E126: 0 | I126: =D126-SUM(E126:H126) -> 410.5
B127: 04.18 | C127: Manutenção de Sauna | D127: =IF(ISERROR(VLOOKUP(C127,[1]DesSin02.rpt!$A$1:$H$200,6,FALSE))=TRUE,0,VLOOKUP(C127,[1]DesSin02.rpt!$A$1:$H$200,6,FALSE)) -> 0 | I127: =D127-SUM(E127:H127) -> 0
B128: 04.19 | C128: Limpeza de Fossa e/ou Caixa de Gordura | D128: =IF(ISERROR(VLOOKUP(C128,[1]DesSin02.rpt!$A$1:$H$200,6,FALSE))=TRUE,0,VLOOKUP(C128,[1]DesSin02.rpt!$A$1:$H$200,6,FALSE)) -> 2250 | I128: =D128-SUM(E128:H128) -> 2250
B129: 04.20 | C129: Limpeza Caixa D`água | D129: =IF(ISERROR(VLOOKUP(C129,[1]DesSin02.rpt!$A$1:$H$200,6,FALSE))=TRUE,0,VLOOKUP(C129,[1]DesSin02.rpt!$A$1:$H$200,6,FALSE)) -> 2965.83 | I129: =D129-SUM(E129:H129) -> 2965.83
B130: 04.21 | C130: Manutenção E.T.A. | D130: =IF(ISERROR(VLOOKUP(C130,[1]DesSin02.rpt!$A$1:$H$200,6,FALSE))=TRUE,0,VLOOKUP(C130,[1]DesSin02.rpt!$A$1:$H$200,6,FALSE)) -> 0 | I130: =D130-SUM(E130:H130) -> 0
B131: 04.22 | C131: Compra de móveis (conta inativa) | D131: =IF(ISERROR(VLOOKUP(C131,[1]DesSin02.rpt!$A$1:$H$200,6,FALSE))=TRUE,0,VLOOKUP(C131,[1]DesSin02.rpt!$A$1:$H$200,6,FALSE)) -> 0 | I131: =D131-SUM(E131:H131) -> 0
B132: 04.23 | C132: Confecção/Manut. Poço Semi-Artesiano | D132: =IF(ISERROR(VLOOKUP(C132,[1]DesSin02.rpt!$A$1:$H$200,6,FALSE))=TRUE,0,VLOOKUP(C132,[1]DesSin02.rpt!$A$1:$H$200,6,FALSE)) -> 0 | I132: =D132-SUM(E132:H132) -> 0
B133: 04.24 | C133: Desratização | D133: =IF(ISERROR(VLOOKUP(C133,[1]DesSin02.rpt!$A$1:$H$200,6,FALSE))=TRUE,0,VLOOKUP(C133,[1]DesSin02.rpt!$A$1:$H$200,6,FALSE)) -> 0 | I133: =D133-SUM(E133:H133) -> 0
B134: 04.25 | C134: Manutenção de Câmeras de Segurança | D134: =IF(ISERROR(VLOOKUP(C134,[1]DesSin02.rpt!$A$1:$H$200,6,FALSE))=TRUE,0,VLOOKUP(C134,[1]DesSin02.rpt!$A$1:$H$200,6,FALSE)) -> 0 | I134: =D134-SUM(E134:H134) -> 0
B135: 04.26 | C135: Laudo de Autovistoria Predial | D135: =IF(ISERROR(VLOOKUP(C135,[1]DesSin02.rpt!$A$1:$H$200,6,FALSE))=TRUE,0,VLOOKUP(C135,[1]DesSin02.rpt!$A$1:$H$200,6,FALSE)) -> 0 | E135: =-D146+D156 -> -27769.79 | I135: =D135-SUM(E135:H135) -> 27769.79
B136: 04.27 | C136: Sistema de Combate a Incêndio | D136: =IF(ISERROR(VLOOKUP(C136,[1]DesSin02.rpt!$A$1:$H$200,6,FALSE))=TRUE,0,VLOOKUP(C136,[1]DesSin02.rpt!$A$1:$H$200,6,FALSE)) -> 0 | E136: =-D205 -> -436.71 | F136: 17791.48 | G136: 2487.01 | I136: =D136-SUM(E136:H136) -> -19841.78
A138: 05 | C138: Tarifas Bancárias | D138: =SUM(D140:D143) -> 1013.92 | I138: =SUM(I140:I145) -> 1013.92
B140: 05.01 | C140: CPMF | D140: =IF(ISERROR(VLOOKUP(C140,[1]DesSin02.rpt!$A$1:$H$200,6,FALSE))=TRUE,0,VLOOKUP(C140,[1]DesSin02.rpt!$A$1:$H$200,6,FALSE)) -> 0 | I140: =D140-SUM(E140:H140) -> 0
B141: 05.02 | C141: IOF | D141: =IF(ISERROR(VLOOKUP(C141,[1]DesSin02.rpt!$A$1:$H$200,6,FALSE))=TRUE,0,VLOOKUP(C141,[1]DesSin02.rpt!$A$1:$H$200,6,FALSE)) -> 0 | I141: =D141-SUM(E141:H141) -> 0
B142: 05.03 | C142: Juros | D142: =IF(ISERROR(VLOOKUP(C142,[1]DesSin02.rpt!$A$1:$H$200,6,FALSE))=TRUE,0,VLOOKUP(C142,[1]DesSin02.rpt!$A$1:$H$200,6,FALSE)) -> 0 | I142: =D142-SUM(E142:H142) -> 0
B143: 05.04 | C143: Tarifas Bancárias | D143: =IF(ISERROR(VLOOKUP(C143,[1]DesSin02.rpt!$A$1:$H$200,6,FALSE))=TRUE,0,VLOOKUP(C143,[1]DesSin02.rpt!$A$1:$H$200,6,FALSE)) -> 1013.92 | I143: =D143-SUM(E143:H143) -> 1013.92
B144: 05.05 | C144: Título de Capitalização | D144: =IF(ISERROR(VLOOKUP(C144,[1]DesSin02.rpt!$A$1:$H$200,6,FALSE))=TRUE,0,VLOOKUP(C144,[1]DesSin02.rpt!$A$1:$H$200,6,FALSE)) -> 0 | I144: =D144-SUM(E144:H144) -> 0
A146: 06 | C146: Despesas Diversas | D146: =SUM(D148:D178) -> 32336.18 | I146: =SUM(I148:I179) -> 4566.39
B148: 06.01 | C148: Xerox (conta inativa) | D148: =IF(ISERROR(VLOOKUP(C148,[1]DesSin02.rpt!$A$1:$H$200,6,FALSE))=TRUE,0,VLOOKUP(C211,[1]DesSin02.rpt!$A$1:$H$200,6,FALSE)) -> 0 | E148: =+D146-D156 -> 27769.79 | I148: =D148-SUM(E148:H148) -> -27769.79
B149: 06.02 | C149: Correio (conta inativa) | D149: =IF(ISERROR(VLOOKUP(C149,[1]DesSin02.rpt!$A$1:$H$200,6,FALSE))=TRUE,0,VLOOKUP(C149,[1]DesSin02.rpt!$A$1:$H$200,6,FALSE)) -> 0 | I149: =D149-SUM(E149:H149) -> 0
...

Sheet  P R E V I S Ã O 
A7: PREVISÃO ORÇAMENTÁRIA
C9: RECEITAS | D9: VALOR MENSAL
B10: 1 | C10: Taxas de Condomínio | D10: =' C O N T A S '!D15 -> 15446.72 | E10: =+D10 -> 15446.72
A11: =COUNT(B$9:B10) -> 1 | B11: =IF(D11=0,"",A11+1) -> 2 | C11: Fundo de Reserva | D11: =' C O N T A S '!D16 -> 1544.56 | E11: =+D11 -> 1544.56
A12: =COUNT(B$9:B11) -> 2 | B12: =IF(D12=0,"",A12+1) | C12: Fundo de Obra | D12: =' C O N T A S '!D17 -> 0 | E12: =+D12 -> 0
A13: =COUNT(B$9:B12) -> 2 | B13: =IF(D13=0,"",A13+1) -> 3 | C13: Água | D13: =' C O N T A S '!D49 -> 2796.58 | E13: =+D13 -> 2796.58
A14: =COUNT(B$9:B13) -> 3 | B14: =IF(D14=0,"",A14+1) | C14: Gás | D14: =' C O N T A S '!D20 -> 0 | E14: =+D14 -> 0
A15: =COUNT(B$9:B14) -> 3 | B15: =IF(D15=0,"",A15+1) | C15: Luz | D15: =' C O N T A S '!D22 -> 0 | E15: =+D15 -> 0
A16: =COUNT(B$9:B15) -> 3 | B16: =IF(D16=0,"",A16+1) | C16: Tv a Cabo | D16: =' C O N T A S '!D24 -> 0 | E16: =+D16 -> 0
A17: =COUNT(B$9:B16) -> 3 | B17: =IF(D17=0,"",A17+1) | C17: Internet | D17: =' C O N T A S '!D41 -> 0 | E17: =+D17 -> 0
C19: TOTAL | D19: =SUM(D10:D18) -> 19787.86
C21: DESPESAS | D21: VALOR ANUAL
B22: 1 | C22: Despesas com Pessoal | D22: =' C O N T A S '!$I$64 -> 50680.23 | E22: =D22/' P R E V I S Ã O (2)'!$E$11 -> 4223.3525 | F22: =+D22/12 -> 4223.3525
A23: =COUNT(B$21:B22) -> 1 | B23: =IF(D23<0.01,"",A23+1) -> 2 | C23: Luz do Condomínio | D23: =' C O N T A S '!$I$98+' C O N T A S '!$I$103 -> 9700.19 | E23: =D23/' P R E V I S Ã O (2)'!$E$11 -> 808.34917
A24: =COUNT(B$21:B23) -> 2 | B24: =IF(D24<0.01,"",A24+1) -> 3 | C24: Água do Condomínio | D24: =' C O N T A S '!$I$99 -> 59303.2 | E24: =D24/' P R E V I S Ã O (2)'!$E$11 -> 4941.9333
A25: =COUNT(B$21:B24) -> 3 | B25: =IF(D25<0.01,"",A25+1) | C25: Telefone do Condomínio | D25: =' C O N T A S '!$I$100 -> 0 | E25: =D25/' P R E V I S Ã O (2)'!$E$11 -> 0
A26: =COUNT(B$21:B25) -> 3 | B26: =IF(D26<0.01,"",A26+1) | C26: Gás do Condomínio | D26: =' C O N T A S '!$I$104 -> 0 | E26: =D26/' P R E V I S Ã O (2)'!$E$11 -> 0
A27: =COUNT(B$21:B26) -> 3 | B27: =IF(D27<0.01,"",A27+1) -> 4 | C27: Material de Limpeza | D27: =' C O N T A S '!$I$119 -> 2649.6 | E27: =D27/' P R E V I S Ã O (2)'!$E$11 -> 220.8
A28: =COUNT(B$21:B27) -> 4 | B28: =IF(D28<0.01,"",A28+1) -> 5 | C28: Gastos com conservação | D28: =+' C O N T A S '!$I$108-' C O N T A S '!$I$119 -> 16806.94 | E28: =D28/' P R E V I S Ã O (2)'!$E$11 -> 1400.5783
A29: =COUNT(B$21:B28) -> 5 | B29: =IF(D29<0.01,"",A29+1) -> 6 | C29: Tarifas Bancárias | D29: =' C O N T A S '!$I$138 -> 1013.92 | E29: =D29/' P R E V I S Ã O (2)'!$E$11 -> 84.493333
A30: =COUNT(B$21:B29) -> 6 | B30: =IF(D30<0.01,"",A30+1) -> 7 | C30: Seguro de Incêndio Obrigatório | D30: =' C O N T A S '!$I$156 -> 4566.39 | E30: =D30/' P R E V I S Ã O (2)'!$E$11 -> 380.5325
A31: =COUNT(B$21:B30) -> 7 | B31: =IF(D31<0.01,"",A31+1) | C31: Outras despesas diversas | D31: =+' C O N T A S '!$I$146-' C O N T A S '!$I$150-' C O N T A S '!$I$153-' C O N T A S '!$I$154-' C O N T A S '!$I$156-' C O N T A S '!$I$159-' C O N T A S '!$I$160-' C O N T A S '!$I$164-' C O N T A S '!$I$166-' C O N T A S '!$I$168-' C O N T A S '!$I$169 -> -1.8189894e-12 | E31: =D31/' P R E V I S Ã O (2)'!$E$11 -> -1.5158245e-13
A32: =COUNT(B$21:B31) -> 7 | B32: =IF(D32<0.01,"",A32+1) -> 8 | C32: Contrato Manutenção de Elevador | D32: =' C O N T A S '!$I$193 -> 10561.44 | E32: =D32/' P R E V I S Ã O (2)'!$E$11 -> 880.12
A33: =COUNT(B$21:B32) -> 8 | B33: =IF(D33<0.01,"",A33+1) | C33: Contrato de Manutenção do Jardim | D33: =' C O N T A S '!$I$194 -> 0 | E33: =D33/' P R E V I S Ã O (2)'!$E$11 -> 0
A34: =COUNT(B$21:B33) -> 8 | B34: =IF(D34<0.01,"",A34+1) | C34: Contrato TV a Cabo | D34: =' C O N T A S '!$I$195 -> 0 | E34: =D34/' P R E V I S Ã O (2)'!$E$11 -> 0
A35: =COUNT(B$21:B34) -> 8 | B35: =IF(D35<0.01,"",A35+1) | C35: Contrato Manutenção de E.T.A. | D35: =' C O N T A S '!$I$196 -> 0 | E35: =D35/' P R E V I S Ã O (2)'!$E$11 -> 0
A36: =COUNT(B$21:B35) -> 8 | B36: =IF(D36<0.01,"",A36+1) | C36: Contrato de Manut. Hidráulica/Elétrica | D36: =' C O N T A S '!$I$197 -> 0 | E36: =D36/' P R E V I S Ã O (2)'!$E$11 -> 0
A37: =COUNT(B$21:B36) -> 8 | B37: =IF(D37<0.01,"",A37+1) | C37: Contrato Manut. interf., câmera, portão e antena | D37: =' C O N T A S '!$I$198 -> 0 | E37: =D37/' P R E V I S Ã O (2)'!$E$11 -> 0
A38: =COUNT(B$21:B37) -> 8 | B38: =IF(D38<0.01,"",A38+1) | C38: Contrato Vigia Noturno | D38: =' C O N T A S '!$I$199 -> 0 | E38: =D38/' P R E V I S Ã O (2)'!$E$11 -> 0
A39: =COUNT(B$21:B38) -> 8 | B39: =IF(D39<0.01,"",A39+1) -> 9 | C39: Contrato Sena Contabilidade | D39: =' C O N T A S '!$I$200 -> 5234.52 | E39: =D39/' P R E V I S Ã O (2)'!$E$11 -> 436.21
A40: =COUNT(B$21:B39) -> 9 | B40: =IF(D40<0.01,"",A40+1) -> 10 | C40: Contrato Prestação Serviço Administração | D40: =' C O N T A S '!$I$201 -> 16536 | E40: =D40/' P R E V I S Ã O (2)'!$E$11 -> 1378
A41: =COUNT(B$21:B40) -> 10 | B41: =IF(D41<0.01,"",A41+1) | C41: Contrato Manutenção Interfonia/Portão/Antena | D41: =' C O N T A S '!$I$202 -> 0 | E41: =D41/' P R E V I S Ã O (2)'!$E$11 -> 0
A42: =COUNT(B$21:B41) -> 10 | B42: =IF(D42<0.01,"",A42+1) | C42: Contrato de Assinatura de Internet | D42: =' C O N T A S '!$I$203 -> 0 | E42: =D42/' P R E V I S Ã O (2)'!$E$11 -> 0
A43: =COUNT(B$21:B42) -> 10 | B43: =IF(D43<0.01,"",A43+1) | C43: Despesas Cartoriais e Honorários | D43: =+' C O N T A S '!$I$205 -> 0 | E43: =D43/' P R E V I S Ã O (2)'!$E$11 -> 0
A44: =COUNT(B$21:B43) -> 10 | B44: =IF(D44<0.01,"",A44+1) -> 11 | C44: Despesas Administrativas | D44: =+' C O N T A S '!I234 -> 2278.7 | E44: =D44/' P R E V I S Ã O (2)'!$E$11 -> 189.89167
A45: =COUNT(B$21:B44) -> 11 | B45: =IF(D45<0.01,"",A45+1) -> 12 | C45: Pró-labore do Síndico | D45: =+' C O N T A S '!$I$256 -> 10199.8 | E45: =D45/' P R E V I S Ã O (2)'!$E$11 -> 849.98333
A46: =COUNT(B$21:B45) -> 12 | B46: =IF(D46<0.01,"",A46+1) | E46: =D46/' P R E V I S Ã O (2)'!$E$11 -> 0
A47: =COUNT(B$21:B46) -> 12 | B47: =IF(D47<0.01,"",A47+1) | E47: =D47/' P R E V I S Ã O (2)'!$E$11 -> 0
C48: SUBTOTAL | D48: =SUM(D22:D47) -> 189530.93 | E48: Inflação | F48: =+D48/12 -> 15794.244
B49: 99 | C49: ="PREVISÃO DE INFLAÇÃO - " & E49*100 & " %" -> PREVISÃO DE INFLAÇÃO - 10 % | D49: =D48*E49 -> 18953.093 | E49: =' P R E V I S Ã O (2)'!F48 -> 0.1
C51: TOTAL | D51: =D48+D49 -> 208484.02 | E51: =D51/' P R E V I S Ã O (2)'!$E$11 -> 17373.669
C53: =IF(D53<0,"SALDO ( DÉFICIT )","SALDO ( SUPERÁVIT )") -> SALDO ( DÉFICIT ) | D53: =D19-D51 -> -188696.16 | E53: =D53/' P R E V I S Ã O (2)'!$E$11 -> -15724.68
D55: =+D48/12 -> 15794.244
B67: Cabo Frio, | D67: PORTO REAL IMÓVEIS

Sheet  P R E V I S Ã O  (2)
A6: =VLOOKUP(Cadastro!A4,Cadastro!B3:C145,2,FALSE) -> COND. ED. RESIDENCIAL BARRAMARES XX
A8: PREVISÃO ORÇAMENTÁRIA PARA 2026/2027
C10: RECEITAS | D10: VALOR MÉDIO MENSAL
B11: 1 | C11: Taxas de Condomínio | D11: =IF(ISERROR(VLOOKUP(B11,' P R E V I S Ã O '!$B$10:$E$18,4,FALSE)=TRUE),"",VLOOKUP(B11,' P R E V I S Ã O '!$B$10:$E$18,4,FALSE)) -> 15446.72 | E11: 12 | F11: 1
B12: 2 | C12: =IF(ISERROR(VLOOKUP(B12,' P R E V I S Ã O '!B$10:D$18,2,FALSE)=TRUE),"",VLOOKUP(B12,' P R E V I S Ã O '!$B$10:$D$18,2,FALSE)) -> Fundo de Reserva | D12: =IF(ISERROR(VLOOKUP(B12,' P R E V I S Ã O '!$B$10:$E$18,4,FALSE)=TRUE),"",VLOOKUP(B12,' P R E V I S Ã O '!$B$10:$E$18,4,FALSE)) -> 1544.56 | F12: 2
B13: 3 | C13: =IF(ISERROR(VLOOKUP(B13,' P R E V I S Ã O '!B$10:D$18,2,FALSE)=TRUE),"",VLOOKUP(B13,' P R E V I S Ã O '!$B$10:$D$18,2,FALSE)) -> Água | D13: =IF(ISERROR(VLOOKUP(B13,' P R E V I S Ã O '!$B$10:$E$18,4,FALSE)=TRUE),"",VLOOKUP(B13,' P R E V I S Ã O '!$B$10:$E$18,4,FALSE)) -> 2796.58 | F13: 3
B14: 4 | C14: =IF(ISERROR(VLOOKUP(B14,' P R E V I S Ã O '!B$10:D$18,2,FALSE)=TRUE),"",VLOOKUP(B14,' P R E V I S Ã O '!$B$10:$D$18,2,FALSE)) | D14: =IF(ISERROR(VLOOKUP(B14,' P R E V I S Ã O '!$B$10:$E$18,4,FALSE)=TRUE),"",VLOOKUP(B14,' P R E V I S Ã O '!$B$10:$E$18,4,FALSE)) | F14: 4
B15: 5 | C15: =IF(ISERROR(VLOOKUP(B15,' P R E V I S Ã O '!B$10:D$18,2,FALSE)=TRUE),"",VLOOKUP(B15,' P R E V I S Ã O '!$B$10:$D$18,2,FALSE)) | D15: =IF(ISERROR(VLOOKUP(B15,' P R E V I S Ã O '!$B$10:$E$18,4,FALSE)=TRUE),"",VLOOKUP(B15,' P R E V I S Ã O '!$B$10:$E$18,4,FALSE)) | F15: 5
B16: 6 | C16: =IF(ISERROR(VLOOKUP(B16,' P R E V I S Ã O '!B$10:D$18,2,FALSE)=TRUE),"",VLOOKUP(B16,' P R E V I S Ã O '!$B$10:$D$18,2,FALSE)) | D16: =IF(ISERROR(VLOOKUP(B16,' P R E V I S Ã O '!$B$10:$E$18,4,FALSE)=TRUE),"",VLOOKUP(B16,' P R E V I S Ã O '!$B$10:$E$18,4,FALSE)) | F16: 6
B17: 7 | C17: =IF(ISERROR(VLOOKUP(B17,' P R E V I S Ã O '!B$10:D$18,2,FALSE)=TRUE),"",VLOOKUP(B17,' P R E V I S Ã O '!$B$10:$D$18,2,FALSE)) | D17: =IF(ISERROR(VLOOKUP(B17,' P R E V I S Ã O '!$B$10:$E$18,4,FALSE)=TRUE),"",VLOOKUP(B17,' P R E V I S Ã O '!$B$10:$E$18,4,FALSE)) | F17: 7
B18: 8 | C18: =IF(ISERROR(VLOOKUP(B18,' P R E V I S Ã O '!B$10:D$18,2,FALSE)=TRUE),"",VLOOKUP(B18,' P R E V I S Ã O '!$B$10:$D$18,2,FALSE)) | D18: =IF(ISERROR(VLOOKUP(B18,' P R E V I S Ã O '!$B$10:$E$18,4,FALSE)=TRUE),"",VLOOKUP(B18,' P R E V I S Ã O '!$B$10:$E$18,4,FALSE)) | F18: 8
C19: TOTAL | D19: =SUM(D11:D18) -> 19787.86 | F19: 9
F20: 10
C21: DESPESAS | D21: VALOR MÉDIO MENSAL | F21: 11
B22: 1 | C22: =IF(ISERROR(VLOOKUP(B22,' P R E V I S Ã O '!$B$22:$D$47,2,FALSE)=TRUE),"",VLOOKUP(B22,' P R E V I S Ã O '!$B$22:$D$47,2,FALSE)) -> Despesas com Pessoal | D22: =IF(ISERROR(VLOOKUP(B22,' P R E V I S Ã O '!$B$22:$E$47,4,FALSE)=TRUE),"",VLOOKUP(B22,' P R E V I S Ã O '!$B$22:$E$47,4,FALSE)) -> 4223.3525 | F22: 12
B23: 2 | C23: =IF(ISERROR(VLOOKUP(B23,' P R E V I S Ã O '!$B$22:$D$47,2,FALSE)=TRUE),"",VLOOKUP(B23,' P R E V I S Ã O '!$B$22:$D$47,2,FALSE)) -> Luz do Condomínio | D23: =IF(ISERROR(VLOOKUP(B23,' P R E V I S Ã O '!$B$22:$E$47,4,FALSE)=TRUE),"",VLOOKUP(B23,' P R E V I S Ã O '!$B$22:$E$47,4,FALSE)) -> 808.34917
B24: 3 | C24: =IF(ISERROR(VLOOKUP(B24,' P R E V I S Ã O '!$B$22:$D$47,2,FALSE)=TRUE),"",VLOOKUP(B24,' P R E V I S Ã O '!$B$22:$D$47,2,FALSE)) -> Água do Condomínio | D24: =IF(ISERROR(VLOOKUP(B24,' P R E V I S Ã O '!$B$22:$E$47,4,FALSE)=TRUE),"",VLOOKUP(B24,' P R E V I S Ã O '!$B$22:$E$47,4,FALSE)) -> 4941.9333
B25: 4 | C25: =IF(ISERROR(VLOOKUP(B25,' P R E V I S Ã O '!$B$22:$D$47,2,FALSE)=TRUE),"",VLOOKUP(B25,' P R E V I S Ã O '!$B$22:$D$47,2,FALSE)) -> Material de Limpeza | D25: =IF(ISERROR(VLOOKUP(B25,' P R E V I S Ã O '!$B$22:$E$47,4,FALSE)=TRUE),"",VLOOKUP(B25,' P R E V I S Ã O '!$B$22:$E$47,4,FALSE)) -> 220.8
B26: 5 | C26: =IF(ISERROR(VLOOKUP(B26,' P R E V I S Ã O '!$B$22:$D$47,2,FALSE)=TRUE),"",VLOOKUP(B26,' P R E V I S Ã O '!$B$22:$D$47,2,FALSE)) -> Gastos com conservação | D26: =IF(ISERROR(VLOOKUP(B26,' P R E V I S Ã O '!$B$22:$E$47,4,FALSE)=TRUE),"",VLOOKUP(B26,' P R E V I S Ã O '!$B$22:$E$47,4,FALSE)) -> 1400.5783
B27: 6 | C27: =IF(ISERROR(VLOOKUP(B27,' P R E V I S Ã O '!$B$22:$D$47,2,FALSE)=TRUE),"",VLOOKUP(B27,' P R E V I S Ã O '!$B$22:$D$47,2,FALSE)) -> Tarifas Bancárias | D27: =IF(ISERROR(VLOOKUP(B27,' P R E V I S Ã O '!$B$22:$E$47,4,FALSE)=TRUE),"",VLOOKUP(B27,' P R E V I S Ã O '!$B$22:$E$47,4,FALSE)) -> 84.493333
B28: 7 | C28: =IF(ISERROR(VLOOKUP(B28,' P R E V I S Ã O '!$B$22:$D$47,2,FALSE)=TRUE),"",VLOOKUP(B28,' P R E V I S Ã O '!$B$22:$D$47,2,FALSE)) -> Seguro de Incêndio Obrigatório | D28: =IF(ISERROR(VLOOKUP(B28,' P R E V I S Ã O '!$B$22:$E$47,4,FALSE)=TRUE),"",VLOOKUP(B28,' P R E V I S Ã O '!$B$22:$E$47,4,FALSE)) -> 380.5325
B29: 8 | C29: =IF(ISERROR(VLOOKUP(B29,' P R E V I S Ã O '!$B$22:$D$47,2,FALSE)=TRUE),"",VLOOKUP(B29,' P R E V I S Ã O '!$B$22:$D$47,2,FALSE)) -> Contrato Manutenção de Elevador | D29: =IF(ISERROR(VLOOKUP(B29,' P R E V I S Ã O '!$B$22:$E$47,4,FALSE)=TRUE),"",VLOOKUP(B29,' P R E V I S Ã O '!$B$22:$E$47,4,FALSE)) -> 880.12
B30: 9 | C30: =IF(ISERROR(VLOOKUP(B30,' P R E V I S Ã O '!$B$22:$D$47,2,FALSE)=TRUE),"",VLOOKUP(B30,' P R E V I S Ã O '!$B$22:$D$47,2,FALSE)) -> Contrato Sena Contabilidade | D30: =IF(ISERROR(VLOOKUP(B30,' P R E V I S Ã O '!$B$22:$E$47,4,FALSE)=TRUE),"",VLOOKUP(B30,' P R E V I S Ã O '!$B$22:$E$47,4,FALSE)) -> 436.21
B31: 10 | C31: =IF(ISERROR(VLOOKUP(B31,' P R E V I S Ã O '!$B$22:$D$47,2,FALSE)=TRUE),"",VLOOKUP(B31,' P R E V I S Ã O '!$B$22:$D$47,2,FALSE)) -> Contrato Prestação Serviço Administração | D31: =IF(ISERROR(VLOOKUP(B31,' P R E V I S Ã O '!$B$22:$E$47,4,FALSE)=TRUE),"",VLOOKUP(B31,' P R E V I S Ã O '!$B$22:$E$47,4,FALSE)) -> 1378
B32: 11 | C32: =IF(ISERROR(VLOOKUP(B32,' P R E V I S Ã O '!$B$22:$D$47,2,FALSE)=TRUE),"",VLOOKUP(B32,' P R E V I S Ã O '!$B$22:$D$47,2,FALSE)) -> Despesas Administrativas | D32: =IF(ISERROR(VLOOKUP(B32,' P R E V I S Ã O '!$B$22:$E$47,4,FALSE)=TRUE),"",VLOOKUP(B32,' P R E V I S Ã O '!$B$22:$E$47,4,FALSE)) -> 189.89167
B33: 12 | C33: =IF(ISERROR(VLOOKUP(B33,' P R E V I S Ã O '!$B$22:$D$47,2,FALSE)=TRUE),"",VLOOKUP(B33,' P R E V I S Ã O '!$B$22:$D$47,2,FALSE)) -> Pró-labore do Síndico | D33: =IF(ISERROR(VLOOKUP(B33,' P R E V I S Ã O '!$B$22:$E$47,4,FALSE)=TRUE),"",VLOOKUP(B33,' P R E V I S Ã O '!$B$22:$E$47,4,FALSE)) -> 849.98333
B34: 13 | C34: =IF(ISERROR(VLOOKUP(B34,' P R E V I S Ã O '!$B$22:$D$47,2,FALSE)=TRUE),"",VLOOKUP(B34,' P R E V I S Ã O '!$B$22:$D$47,2,FALSE)) | D34: =IF(ISERROR(VLOOKUP(B34,' P R E V I S Ã O '!$B$22:$E$47,4,FALSE)=TRUE),"",VLOOKUP(B34,' P R E V I S Ã O '!$B$22:$E$47,4,FALSE))
... B45: 24 | C45: =IF(ISERROR(VLOOKUP(B45,' P R E V I S Ã O '!$B$22:$D$47,2,FALSE)=TRUE),"",VLOOKUP(B45,' P R E V I S Ã O '!$B$22:$D$47,2,FALSE)) | D45: =IF(ISERROR(VLOOKUP(B45,' P R E V I S Ã O '!$B$22:$E$47,4,FALSE)=TRUE),"",VLOOKUP(B45,' P R E V I S Ã O '!$B$22:$E$47,4,FALSE))
B46: 25 | C46: =IF(ISERROR(VLOOKUP(B46,' P R E V I S Ã O '!$B$22:$D$47,2,FALSE)=TRUE),"",VLOOKUP(B46,' P R E V I S Ã O '!$B$22:$D$47,2,FALSE)) | D46: =IF(ISERROR(VLOOKUP(B46,' P R E V I S Ã O '!$B$22:$E$47,4,FALSE)=TRUE),"",VLOOKUP(B46,' P R E V I S Ã O '!$B$22:$E$47,4,FALSE)) | G46: c/ FR | H46: s/ FR
C47: SUBTOTAL | D47: =SUM(D22:D46) -> 15794.244 | F47: Inflação | G47: Aumento | H47: Aumento
C48: ="Aumento previsto ( salário,tarifas pub., serviços) = " & F48*100 & " %" -> Aumento previsto ( salário,tarifas pub., serviços) = 10 % | D48: =D47*F48 -> 1579.4244 | F48: 0.1 | G48: =+D50/D19-1 -> -0.12200366 | H48: =+D50/(D19-' P R E V I S Ã O '!D11)-1 -> -0.047668537
C50: TOTAL | D50: =D47+D48 -> 17373.669
C52: =IF(D52<0,"SALDO ( DÉFICIT )","SALDO ( SUPERÁVIT )") -> SALDO ( SUPERÁVIT ) | D52: =D19-D50 -> 2414.1914
A54: CONSIDERAÇÕES IMPORTANTES
A56: ="1) Para o cálculo desta previsão, levamos em consideração a média aritmética dos últimos " & E11 & " meses" -> 1) Para o cálculo desta previsão, levamos em consideração a média aritmética dos últimos 12 meses
B88: Cabo Frio, | C88: 11 de junho de 2026 | D88: PORTO REAL IMÓVEIS

Sheet Cadastro
B1: Cadastro de Condomínios
B3: 1 | C3: CENTRO COMERCIAL D´COSTA MARTINS
A4: 102 | B4: 2 | C4: CENTRO EMPRESARIAL DR. SYLVIO COSTA
A5: 1 | B5: 3 | C5: COND. ALBATROZ II | I5: selecionar a lista dos nomes que estão na coluna C (nõa marcar MATRIZ)
B6: 4 | C6: COND. ALDEIA DOS ANJOS | I6: como? Colocar no c3, segurar a tecla (seta pra cima ou shift) + tecla End + tecla de direção pra baixo
B7: 5 | C7: COND. ALDEIA DOS BURITIS | I7: com o mouse, clicar em Clasificar e Filtar, e Classificar de A à Z
B8: 6 | C8: COND. CONJ. RESIDENCIAL MORADA DAS DUNAS I
B9: 7 | C9: COND. CONJ. RESIDENCIAL SAINT TROPEZ
B10: 8 | C10: COND. DA PRAINHA
B11: 9 | C11: COND. DAS AROEIRAS
B12: 10 | C12: COND. ED. AGATHA III
B13: 11 | C13: COND. ED. ALBATROZ
B14: 12 | C14: COND. ED. ANDREI NORILLER
B15: 13 | C15: COND. ED. ANGELINA
B16: 14 | C16: COND. ED. ATLÂNTICO
B17: 15 | C17: COND. ED. BARRAMAR
B18: 16 | C18: COND. ED. BEACH TOWN RESIDENCE
B19: 17 | C19: COND. ED. BELLA VISTA
... B139: 137 | C139: COND. VILLAGE DO SUL VI
C212: ACRESCENTAR LINHAS

Sheet Comp. Desp-Rec
A8: =VLOOKUP(Cadastro!#REF!,Cadastro!B3:C44,2,FALSE) -> #REF!
A10: Comparativo em Percentuais entre Despesas e Receitas
C12: RECEITAS | D12: VALOR MÉDIO MENSAL
B13: 1 | C13: Taxas de Condomínio | D13: =' P R E V I S Ã O '!D10 -> 15446.72 | E13: 12 | F13: 1
B14: 2 | C14: =IF(ISERROR(VLOOKUP(B14,' P R E V I S Ã O '!B10:D18,2,FALSE)=TRUE),"",VLOOKUP(B14,' P R E V I S Ã O '!$B$10:$D$18,2,FALSE)) -> Fundo de Reserva | D14: =IF(ISERROR(VLOOKUP(B14,' P R E V I S Ã O '!$B$10:$D$18,3,FALSE)=TRUE),"",VLOOKUP(B14,' P R E V I S Ã O '!$B$10:$D$18,3,FALSE)) -> 1544.56 | F14: 2
F15: 3
C16: TOTAL | D16: =SUM(D13:D14) -> 16991.28 | F16: 4
F17: 5
C18: DESPESAS | D18: VALOR MÉDIO MENSAL | E18: % | F18: 6
B19: 1 | C19: Despesas com Pessoal | D19: =' P R E V I S Ã O '!E22 -> 4223.3525 | E19: =IF(ISERROR(D19/$D$16%)=TRUE,"",D19/$D$16%) -> 24.856 | F19: 7
B20: 2 | C20: =IF(ISERROR(VLOOKUP(B20,' P R E V I S Ã O '!$B$22:$D$47,2,FALSE)=TRUE),"",VLOOKUP(B20,' P R E V I S Ã O '!$B$22:$D$47,2,FALSE)) -> Luz do Condomínio | D20: =IF(ISERROR(VLOOKUP(B20,' P R E V I S Ã O '!$B$22:$E$47,4,FALSE)=TRUE),"",VLOOKUP(B20,' P R E V I S Ã O '!$B$22:$E$47,4,FALSE)) -> 808.34917 | E20: =IF(ISERROR(D20/$D$16%)=TRUE,"",D20/$D$16%) -> 4.7574354 | F20: 8
B21: 3 | C21: =IF(ISERROR(VLOOKUP(B21,' P R E V I S Ã O '!$B$22:$D$47,2,FALSE)=TRUE),"",VLOOKUP(B21,' P R E V I S Ã O '!$B$22:$D$47,2,FALSE)) -> Água do Condomínio | D21: =IF(ISERROR(VLOOKUP(B21,' P R E V I S Ã O '!$B$22:$E$47,4,FALSE)=TRUE),"",VLOOKUP(B21,' P R E V I S Ã O '!$B$22:$E$47,4,FALSE)) -> 4941.9333 | E21: =IF(ISERROR(D21/$D$16%)=TRUE,"",D21/$D$16%) -> 29.085115 | F21: 9
B22: 4 | C22: =IF(ISERROR(VLOOKUP(B22,' P R E V I S Ã O '!$B$22:$D$47,2,FALSE)=TRUE),"",VLOOKUP(B22,' P R E V I S Ã O '!$B$22:$D$47,2,FALSE)) -> Material de Limpeza | D22: =IF(ISERROR(VLOOKUP(B22,' P R E V I S Ã O '!$B$22:$E$47,4,FALSE)=TRUE),"",VLOOKUP(B22,' P R E V I S Ã O '!$B$22:$E$47,4,FALSE)) -> 220.8 | E22: =IF(ISERROR(D22/$D$16%)=TRUE,"",D22/$D$16%) -> 1.2994901 | F22: 10
B23: 5 | C23: =IF(ISERROR(VLOOKUP(B23,' P R E V I S Ã O '!$B$22:$D$47,2,FALSE)=TRUE),"",VLOOKUP(B23,' P R E V I S Ã O '!$B$22:$D$47,2,FALSE)) -> Gastos com conservação | D23: =IF(ISERROR(VLOOKUP(B23,' P R E V I S Ã O '!$B$22:$E$47,4,FALSE)=TRUE),"",VLOOKUP(B23,' P R E V I S Ã O '!$B$22:$E$47,4,FALSE)) -> 1400.5783 | E23: =IF(ISERROR(D23/$D$16%)=TRUE,"",D23/$D$16%) -> 8.2429242 | F23: 11
B24: 6 | C24: =IF(ISERROR(VLOOKUP(B24,' P R E V I S Ã O '!$B$22:$D$47,2,FALSE)=TRUE),"",VLOOKUP(B24,' P R E V I S Ã O '!$B$22:$D$47,2,FALSE)) -> Tarifas Bancárias | D24: =IF(ISERROR(VLOOKUP(B24,' P R E V I S Ã O '!$B$22:$E$47,4,FALSE)=TRUE),"",VLOOKUP(B24,' P R E V I S Ã O '!$B$22:$E$47,4,FALSE)) -> 84.493333 | E24: =IF(ISERROR(D24/$D$16%)=TRUE,"",D24/$D$16%) -> 0.49727468 | F24: 12
B25: 7 | C25: =IF(ISERROR(VLOOKUP(B25,' P R E V I S Ã O '!$B$22:$D$47,2,FALSE)=TRUE),"",VLOOKUP(B25,' P R E V I S Ã O '!$B$22:$D$47,2,FALSE)) -> Seguro de Incêndio Obrigatório | D25: =IF(ISERROR(VLOOKUP(B25,' P R E V I S Ã O '!$B$22:$E$47,4,FALSE)=TRUE),"",VLOOKUP(B25,' P R E V I S Ã O '!$B$22:$E$47,4,FALSE)) -> 380.5325 | E25: =IF(ISERROR(D25/$D$16%)=TRUE,"",D25/$D$16%) -> 2.2395752
B26: 8 | C26: =IF(ISERROR(VLOOKUP(B26,' P R E V I S Ã O '!$B$22:$D$47,2,FALSE)=TRUE),"",VLOOKUP(B26,' P R E V I S Ã O '!$B$22:$D$47,2,FALSE)) -> Contrato Manutenção de Elevador | D26: =IF(ISERROR(VLOOKUP(B26,' P R E V I S Ã O '!$B$22:$E$47,4,FALSE)=TRUE),"",VLOOKUP(B26,' P R E V I S Ã O '!$B$22:$E$47,4,FALSE)) -> 880.12 | E26: =IF(ISERROR(D26/$D$16%)=TRUE,"",D26/$D$16%) -> 5.1798334
B27: 9 | C27: =IF(ISERROR(VLOOKUP(B27,' P R E V I S Ã O '!$B$22:$D$47,2,FALSE)=TRUE),"",VLOOKUP(B27,' P R E V I S Ã O '!$B$22:$D$47,2,FALSE)) -> Contrato Sena Contabilidade | D27: =IF(ISERROR(VLOOKUP(B27,' P R E V I S Ã O '!$B$22:$E$47,4,FALSE)=TRUE),"",VLOOKUP(B27,' P R E V I S Ã O '!$B$22:$E$47,4,FALSE)) -> 436.21 | E27: =IF(ISERROR(D27/$D$16%)=TRUE,"",D27/$D$16%) -> 2.567258
B28: 10 | C28: =IF(ISERROR(VLOOKUP(B28,' P R E V I S Ã O '!$B$22:$D$47,2,FALSE)=TRUE),"",VLOOKUP(B28,' P R E V I S Ã O '!$B$22:$D$47,2,FALSE)) -> Contrato Prestação Serviço Administração | D28: =IF(ISERROR(VLOOKUP(B28,' P R E V I S Ã O '!$B$22:$E$47,4,FALSE)=TRUE),"",VLOOKUP(B28,' P R E V I S Ã O '!$B$22:$E$47,4,FALSE)) -> 1378 | E28: =IF(ISERROR(D28/$D$16%)=TRUE,"",D28/$D$16%) -> 8.1100423
B29: 11 | C29: =IF(ISERROR(VLOOKUP(B29,' P R E V I S Ã O '!$B$22:$D$47,2,FALSE)=TRUE),"",VLOOKUP(B29,' P R E V I S Ã O '!$B$22:$D$47,2,FALSE)) -> Despesas Administrativas | D29: =IF(ISERROR(VLOOKUP(B29,' P R E V I S Ã O '!$B$22:$E$47,4,FALSE)=TRUE),"",VLOOKUP(B29,' P R E V I S Ã O '!$B$22:$E$47,4,FALSE)) -> 189.89167 | E29: =IF(ISERROR(D29/$D$16%)=TRUE,"",D29/$D$16%) -> 1.1175831
B30: 12 | C30: =IF(ISERROR(VLOOKUP(B30,' P R E V I S Ã O '!$B$22:$D$47,2,FALSE)=TRUE),"",VLOOKUP(B30,' P R E V I S Ã O '!$B$22:$D$47,2,FALSE)) -> Pró-labore do Síndico | D30: =IF(ISERROR(VLOOKUP(B30,' P R E V I S Ã O '!$B$22:$E$47,4,FALSE)=TRUE),"",VLOOKUP(B30,' P R E V I S Ã O '!$B$22:$E$47,4,FALSE)) -> 849.98333 | E30: =IF(ISERROR(D30/$D$16%)=TRUE,"",D30/$D$16%) -> 5.0024679
C31: SUBTOTAL | D31: =SUM(D19:D30) -> 15794.244
B32: 99 | C32: ="Aumento previsto(salário,tarifas pub.,serviços) = " & E32*100 & " %" -> Aumento previsto(salário,tarifas pub.,serviços) = 10 % | D32: =D31*E32 -> 1579.4244 | E32: =IF(ISERROR(VLOOKUP(B32,' P R E V I S Ã O '!$B$22:$E$49,4,FALSE)=TRUE),"",VLOOKUP(B32,' P R E V I S Ã O '!$B$22:$E$49,4,FALSE)) -> 0.1
C34: TOTAL | D34: =D31+D32 -> 17373.669
C36: =IF(D36<0,"SALDO ( DÉFICIT )","SALDO ( SUPERÁVIT )") -> SALDO ( DÉFICIT ) | D36: =D16-D34 -> -382.38858
